README.txt
setup.py
./helptext/__init__.py
./helptext/admin.py
./helptext/models.py
django_helptext.egg-info/PKG-INFO
django_helptext.egg-info/SOURCES.txt
django_helptext.egg-info/dependency_links.txt
django_helptext.egg-info/top_level.txt