Metadata-Version: 1.0
Name: django-helptext
Version: 0.3
Summary: A django application for editing django model field help text in the django admin
Home-page: http://www.bitbucket.org/smulloni/django-helptext/
Author: Jacob Smullyan
Author-email: jsmullyan@gmail.com
License: BSD
Keywords: django help admin
Platform: OS Independent
Classifier: Development Status :: 3 - Alpha
Classifier: Environment :: Web Environment
Classifier: Framework :: Django
Classifier: Intended Audience :: Developers
Classifier: License :: OSI Approved :: BSD License
Classifier: Operating System :: OS Independent
Classifier: Programming Language :: Python
Classifier: Topic :: Internet :: WWW/HTTP :: Dynamic Content
Classifier: Topic :: Software Development :: Libraries :: Python Modules
Classifier: Topic :: Utilities
